pymilldb/__init__.py
pymilldb/decorators.py
pymilldb/graph.py
pymilldb/mdb_client.py
pymilldb/node_iterator.py
pymilldb/packer.py
pymilldb/protocol.py
pymilldb/sampler.py
pymilldb/tensor_store.py
pymilldb-0.0.14.dist-info/LICENSE
pymilldb-0.0.14.dist-info/METADATA
pymilldb-0.0.14.dist-info/WHEEL
pymilldb-0.0.14.dist-info/top_level.txt
pymilldb-0.0.14.dist-info/RECORD
