Metadata-Version: 2.1
Name: pymilldb
Version: 0.0.14
Summary: A python library for MillenniumDB
Home-page: https://github.com/MillenniumDB/PyMillDB
Author: Vicente Calisto
Author-email: vecalisto@uc.cl
Project-URL: Bug Tracker, https://github.com/MillenniumDB/PyMillDB/issues
Classifier: Programming Language :: Python :: 3
Classifier: License :: OSI Approved :: MIT License
Classifier: Operating System :: OS Independent
Requires-Python: >=3.10
License-File: LICENSE
